litio/__init__.py
litio/__main__.py
litio/litio.py
litio/utils/__init__.py
litio/utils/ai.py
litio/utils/info.py
litio/utils/litio.py
litio/utils/modules.py
litio/utils/output.py
litio/utils/tester.py
litio/utils/utils.py
litio-1.6.1.dist-info/LICENSE
litio-1.6.1.dist-info/METADATA
litio-1.6.1.dist-info/WHEEL
litio-1.6.1.dist-info/entry_points.txt
litio-1.6.1.dist-info/top_level.txt
litio-1.6.1.dist-info/RECORD
