Metadata-Version: 2.1
Name: litio
Version: 1.6.1
Summary: A simple tool for testing
Home-page: https://github.com/lizardwine/litio
Author: Lizardwine
Author-email: lizardwine@hotmail.com
License: GPL v3.0
Project-URL: Bug Tracker, https://github.com/lizardwine/litio/issues
Keywords: testing,tester
Classifier: License :: OSI Approved :: GNU General Public License v3 (GPLv3)
Classifier: Development Status :: 5 - Production/Stable
Classifier: Intended Audience :: Developers
Classifier: Natural Language :: English
Classifier: Operating System :: OS Independent
Classifier: Programming Language :: Python :: 3
Classifier: Topic :: Software Development
Requires-Python: >=3.6
License-File: LICENSE
Requires-Dist: PyYAML ==6.0.1
Requires-Dist: rich ==13.7.0
Requires-Dist: openai ==1.3.5
Requires-Dist: python-dotenv ==1.0.0
Requires-Dist: gitpython ==3.1.40
